setup.cfg
setup.py
src/pyrrot.py
src/_pyrrot/__init__.py
src/_pyrrot/comparison.py
src/_pyrrot/config.py
src/_pyrrot/constant.py
src/_pyrrot/main.py
src/_pyrrot/response_builder.py
src/_pyrrot/rule.py
src/_pyrrot/schema.py
src/_pyrrot/templates/config.html
src/pyrrot.egg-info/PKG-INFO
src/pyrrot.egg-info/SOURCES.txt
src/pyrrot.egg-info/dependency_links.txt
src/pyrrot.egg-info/entry_points.txt
src/pyrrot.egg-info/not-zip-safe
src/pyrrot.egg-info/requires.txt
src/pyrrot.egg-info/top_level.txt