Metadata-Version: 1.2
Name: pyrrot
Version: 0.2.3
Summary: pyrrot: É um simples serviço feito em python para simular a resposta de aplicações rest.
Home-page: https://github.com/akiranukamoto/pyrrot
Author: Akira Nukamoto
Author-email: akiranukamoto@gmail.com
License: MIT license
Keywords: mock rest restapi service
Platform: unix
Platform: linux
Platform: osx
Platform: cygwin
Platform: win32
Requires-Python: >=3.6
